<?xml version="1.0" encoding="iso-8859-1"?>
<arqelem>
<tipo assunto="arqueossitio"></tipo>
<identi> Santar </identi>
<descri> Igreja </descri>
<crono> Idade Média</crono>
<lugar> Santar </lugar>
<fregue> Santar </fregue>
<concel> Arcos de Valdevez </concel>
<codadm> 160138 </codadm>
<latitu> 539,1 </latitu>
<longit> 176,1 </longit>
<altitu> 50m </altitu>
<acesso>Junto à aldeia de Santar. O acesso faz-se por estrada municipal a partir da
estrada nacional EN.202-1 (um ramal que liga as EN.101 - Arcos a Ponte da
Barca e EN.202 - Arcos a Ponte de Lima). O monumento não está sinalizado.</acesso>
<desarq>Nas paredes laterais da <liga termo="ábside"> ábside</liga>da igreja
paroquial de Santa Maria de Santar, que foi vigararia de apresentação da
Comenda de Távora, conservam-se, bastante mutilados, alguns <liga termo="modilhão"> modilhões</liga> que compunham o coroamento das paredes da
edificação românica, profundamente alterada por sucessivas remodelações e
ampliações posteriores.</desarq>
<interp>Igreja de fundação medieval.</interp>
<intere>Trata-se de um monumento sem relevância histórica local e de escasso valor
científico e patrimonial, interessando apenas à compreensão da difusão do
<liga termo="românico"> românico</liga> na região.</intere>
<biblio>ALMEIDA, C.A.F.(1987) Alto Minho, (novos guias de Portugal, 5), Editorial
Presença, Lisboa, 1987. </biblio>
<biblio> BARREIROS, M.A. (1926) Egrejas e Capelas Romanicas da Ribeira Lima,
Edições Marques Abreu, Porto, 1926. </biblio>
<autor> Luís Fontes </autor>
<data>04-FEV-1998</data>
</arqelem>